PredictBind/Cli.py
PredictBind/Files.py
PredictBind/Main.py
PredictBind/P2Pocket.py
PredictBind/P2Rank.py
PredictBind/TSV.py
PredictBind/Utils.py
PredictBind/training_data/prank
PredictBind/training_data/prank.bat
PredictBind-1.0.7.dist-info/LICENSE
PredictBind-1.0.7.dist-info/METADATA
PredictBind-1.0.7.dist-info/WHEEL
PredictBind-1.0.7.dist-info/entry_points.txt
PredictBind-1.0.7.dist-info/top_level.txt
PredictBind-1.0.7.dist-info/RECORD
