Metadata-Version: 2.1
Name: PredictBind
Version: 1.0.7
Summary: PredictBind is a wrapped inspired and built around P2Rank as ligand binding site predictor for proteins
Home-page: https://github.com/TamaraVeres/binder
Author: Tamara Veres
Author-email: tamaraveres19@gmail.com
Classifier: Programming Language :: Python :: 3
Classifier: License :: OSI Approved :: MIT License
Classifier: Operating System :: OS Independent
License-File: LICENSE
Requires-Dist: requests
